{"cameraMode":{"drawMode":0,"name":"Shaded","section":"Shading Mode"},"sceneLighting":false,"audioPlay":false,"sceneViewState":{"m_AlwaysRefresh":false,"showFog":true,"showSkybox":false,"showFlares":true,"showImageEffects":true,"showParticleSystems":true,"showVisualEffectGraphs":true,"m_FxEnabled":true},"in2DMode":false,"pivot":{"x":-0.46721458435058596,"y":0.12617111206054688,"z":-7.560995101928711},"rotation":{"x":-0.349526584148407,"y":-0.2612094581127167,"z":0.10243671387434006,"w":-0.8936648964881897},"size":23.378957748413087,"orthographic":false}